{
	"jackie_loop1": {
		"name": "Jackie",
		"portrait": "jackie_portrait.png",
		"text": [
			"..."
		],
	},
	
	"abbie_loop1": {
		"name": "Abbie",
		"portrait": "abbie_portrait.png",
		"text": [
			"..."
		],
	},
	
	"jackie1_1": {
		"name": "Jackie",
		"portrait": "jackie_portrait.png",
		"text": [
			"Oh... Hello",
			"I'm Jackie, the intelligent spitter",
			"I once consumed this artifact that gave me near Shadekin level intelligence",
			"My family stayed the same though",
			"It's been really hard since then..."
		],
	},
	
	"jackie2_1": {
		"name": "Jackie",
		"portrait": "jackie_portrait.png",
		"text": [
			"Oh... Hello again",
			"We've been going pretty deep, huh?",
			"...",
			"Do you seek it too?",
			"The artifact that can change the past?"
		],
		"next": "jackie2_2"
	},
	
	"jackie2_2": {
		"name": "Zaine",
		"portrait": "zaine_portrait.png",
		"text": [
			"Yes"
		],
		"next": "jackie2_3"
	},
	
	"jackie2_3": {
		"name": "Jackie",
		"portrait": "jackie_portrait.png",
		"text": [
			"If we both reach the bottom...",
			"...I hope the artifact has multiple uses, you know?",
			"...",
			"I hope we can both find what we seek",
			"...",
			"Don’t worry...",
			"...Everything is going to be fine",
			"I know it's hard to be here",
			"...",
			"Hey, thanks for talking to me...",
			"This whole thing has been pretty lonely",
		],
	},
	
	"abbie1_1": {
		"name": "Abbie",
		"portrait": "abbie_portrait.png",
		"text": [
			"Hello Looper!",
			"Welcome to the shop"
		],
		"next": "abbie1_2"
	},
	"abbie1_2": {
		"name": "Zaine",
		"portrait": "zaine_portrait.png",
		"text": [
			"What do you sell?"
		],
		"next": "abbie1_3"
	},
	"abbie1_3": {
		"name": "Abbie",
		"portrait": "abbie_portrait.png",
		"text": [
			"A bunch of stuff",
			"Weapons, healing supplies and some magic enhancements",
			"...",
			"I have to ask you though...",
			"You are a Looper, right?"
		],
		"next": "abbie1_4"
	},
	"abbie1_4": {
		"name": "Zaine",
		"portrait": "zaine_portrait.png",
		"text": [
			"I'm not really sure of the definition of 'Looper'"
		],
		"next": "abbie1_5"
	},
	"abbie1_5": {
		"name": "Abbie",
		"portrait": "abbie_portrait.png",
		"text": [
			"Let me rephrase",
			"Are you looking for the artifact that is told to lie at the bottom of this place?"
		],
		"next": "abbie1_6"
	},
	"abbie1_6": {
		"name": "Zaine",
		"portrait": "zaine_portrait.png",
		"text": [
			"I am"
		],
		"next": "abbie1_7"
	},
	"abbie1_7": {
		"name": "Abbie",
		"portrait": "abbie_portrait.png",
		"text": [
			"...",
			"Not to pry in your business...",
			"But I would suggest to stop looking for the artifact.",
			"I think you should leave this place...",
			"...Leave it all behind...",
			"And never come back."
		],
		"next": "abbie1_8"
	},
	"abbie1_8": {
		"name": "Zaine",
		"portrait": "zaine_portrait.png",
		"text": [
			"What?",
			"Why would I do that."
		],
		"next": "abbie1_9"
	},
	"abbie1_9": {
		"name": "Abbie",
		"portrait": "abbie_portrait.png",
		"text": [
			"You see...",
			"All the people that came into my shop looking for the artifact...",
			"...They eventually come back insane."
		],
		"next": "abbie1_10"
	},
	"abbie1_10": {
		"name": "Abbie",
		"portrait": "abbie_portrait.png",
		"text": [
			"...",
			"I don't know what happens to them...",
			"But when I see them again they are aggressive,",
			"They act erratically,",
			"They don't even talk to me...",
			"...They just mumble a strange chant and attack me...",
			"...",
			"Every day I am forced to fight innocent people.",
			"People I talked to...",
			"...",
			"Good people.",
			"...",
			"I think...",
			"...That whatever that artifact is...",
			"It's evil."
		],
		"next": "abbie1_11"
	},
	"abbie1_11": {
		"name": "Zaine",
		"portrait": "zaine_portrait.png",
		"text": [
			"...",
			"Ah! I see...",
			"How much money do you make shopkeep?"
		],
		"next": "abbie1_12"
	},
	"abbie1_12": {
		"name": "Abbie",
		"portrait": "abbie_portrait.png",
		"text": [
			"Uh... what"
		],
		"next": "abbie1_13"
	},
	"abbie1_13": {
		"name": "Zaine",
		"portrait": "zaine_portrait.png",
		"text": [
			"It must be a bustling business...",
			"...It would be really bad if someone snatched the artifact and this dungeon became devoid of people...",
			"...Wouldn't it?"
		],
		"next": "abbie1_14"
	},
	"abbie1_14": {
		"name": "Abbie",
		"portrait": "abbie_portrait.png",
		"text": [
			"What...",
			"...What do you mean?"
		],
		"next": "abbie1_15"
	},
	"abbie1_15": {
		"name": "Zaine",
		"portrait": "zaine_portrait.png",
		"text": [
			"I know what you're trying to do!",
			"Trust me I've met shopkeepers before...",
			"All you care for is money.",
			"You won't stop me from getting the artifact."
		],
		"next": "abbie1_16"
	},
	"abbie1_16": {
		"name": "Abbie",
		"portrait": "abbie_portrait.png",
		"text": [
			"I'm not-",
			"-I just-"
		],
		"next": "abbie1_17"
	},
	"abbie1_17": {
		"name": "Zaine",
		"portrait": "zaine_portrait.png",
		"text": [
			"The artifact is what will fix my life.",
			"It's what will fix everything.",
			"It's what keeps me alive.",
			"It is what gives all the people here hope for a better future.",
			"You should be ashamed."
		],
		"next": "abbie1_18"
	},
	"abbie1_18": {
		"name": "Abbie",
		"portrait": "abbie_portrait.png",
		"text": [
			"I..."
		],
		"next": "abbie1_19"
	},
	"abbie1_19": {
		"name": "Zaine",
		"portrait": "zaine_portrait.png",
		"text": [
			"I think this conversation lasted long enough.",
			"Farewell."
		]
	}
}
